testing.redis-1.1.1-py2.7-nspkg.pth
testing/redis.py
testing.redis-1.1.1.dist-info/DESCRIPTION.rst
testing.redis-1.1.1.dist-info/METADATA
testing.redis-1.1.1.dist-info/RECORD
testing.redis-1.1.1.dist-info/WHEEL
testing.redis-1.1.1.dist-info/metadata.json
testing.redis-1.1.1.dist-info/namespace_packages.txt
testing.redis-1.1.1.dist-info/top_level.txt
