Metadata-Version: 2.0
Name: testing.redis
Version: 1.1.1
Summary: automatically setups a redis instance in a temporary directory, and destroys it after testing
Home-page: https://github.com/tk0miya/testing.redis
Author: Takeshi Komiya
Author-email: i.tkomiya at gmail.com
License: Apache License 2.0
Platform: UNKNOWN
Classifier: Development Status :: 4 - Beta
Classifier: Intended Audience :: Developers
Classifier: License :: OSI Approved :: Apache Software License
Classifier: Programming Language :: Python
Classifier: Programming Language :: Python :: 2.6
Classifier: Programming Language :: Python :: 2.7
Classifier: Programming Language :: Python :: 3.2
Classifier: Programming Language :: Python :: 3.3
Classifier: Programming Language :: Python :: 3.4
Classifier: Programming Language :: Python :: 3.5
Classifier: Topic :: Database
Classifier: Topic :: Software Development
Classifier: Topic :: Software Development :: Testing
Requires-Dist: redis
Requires-Dist: testing.common.database (>=1.1.0)
Provides-Extra: testing
Requires-Dist: mock; extra == 'testing'
Requires-Dist: nose; extra == 'testing'
